hadar/__init__.py
hadar/analyzer/__init__.py
hadar/analyzer/result.py
hadar/optimizer/__init__.py
hadar/optimizer/optimizer.py
hadar/optimizer/utils.py
hadar/optimizer/domain/__init__.py
hadar/optimizer/domain/input.py
hadar/optimizer/domain/numeric.py
hadar/optimizer/domain/output.py
hadar/optimizer/lp/__init__.py
hadar/optimizer/lp/domain.py
hadar/optimizer/lp/mapper.py
hadar/optimizer/lp/optimizer.py
hadar/optimizer/remote/__init__.py
hadar/optimizer/remote/optimizer.py
hadar/viewer/__init__.py
hadar/viewer/abc.py
hadar/viewer/html.py
hadar/workflow/__init__.py
hadar/workflow/pipeline.py
hadar/workflow/shuffler.py
tests/__init__.py
tests/utils.py
tests/analyzer/__init__.py
tests/analyzer/test_result.py
tests/optimizer/__init__.py
tests/optimizer/domain/__init__.py
tests/optimizer/domain/test_input.py
tests/optimizer/domain/test_numeric.py
tests/optimizer/domain/test_output.py
tests/optimizer/it/__init__.py
tests/optimizer/it/test_optimizer.py
tests/optimizer/lp/__init__.py
tests/optimizer/lp/ortools_mock.py
tests/optimizer/lp/test_mapper.py
tests/optimizer/lp/test_optimizer.py
tests/optimizer/remote/__init__.py
tests/optimizer/remote/test_optimizer.py
tests/viewer/__init__.py
tests/viewer/test_html.py
tests/workflow/__init__.py
tests/workflow/test_integration.py
tests/workflow/test_pipeline.py
tests/workflow/test_shuffler.py
hadar-0.5.0.dist-info/AUTHORS.txt
hadar-0.5.0.dist-info/LICENSE
hadar-0.5.0.dist-info/METADATA
hadar-0.5.0.dist-info/WHEEL
hadar-0.5.0.dist-info/top_level.txt
hadar-0.5.0.dist-info/RECORD
