Metadata-Version: 2.1
Name: hadar
Version: 0.5.0
Summary: python adequacy library
Home-page: https://github.com/hadar-simulator/hadar
Author: RTE France
Author-email: francois.jolain@rte-international.com
License: UNKNOWN
Platform: UNKNOWN
Classifier: Programming Language :: Python :: 3
Classifier: License :: OSI Approved :: Apache Software License
Classifier: Operating System :: OS Independent
Requires-Python: >=3.6
Requires-Dist: pandas (<2.0.0,>=1.0.3)
Requires-Dist: numpy (<2.0.0,>=1.18.2)
Requires-Dist: ortools (<8.0.0,>=7.5.7466)
Requires-Dist: plotly (==4.8.1)
Requires-Dist: matplotlib (<4.0.0,>=3.2.1)
Requires-Dist: requests (<3.0.0,>=2.23.0)
Requires-Dist: progress (<2,>=1.5)
Requires-Dist: msgpack (<2.0.0,>=1.0.0)
